mercury/__init__.py
mercury/api_client.py
mercury/configuration.py
mercury/rest.py
mercury/client/__init__.py
mercury/client/api/__init__.py
mercury/client/api/api.py
mercury/client/api/fiddle_api.py
mercury/client/api/marketdata_api.py
mercury/client/api/tradeservice_api.py
mercury/client/model/__init__.py
mercury/client/model/butterfly.py
mercury/client/model/condor.py
mercury/client/model/data_point.py
mercury/client/model/date_value_data_point.py
mercury/client/model/date_value_data_point_double.py
mercury/client/model/direction.py
mercury/client/model/equity_quote.py
mercury/client/model/fiddle.py
mercury/client/model/greeks.py
mercury/client/model/iron_condor.py
mercury/client/model/iv_skew.py
mercury/client/model/iv_skew_data_point.py
mercury/client/model/option_chain.py
mercury/client/model/option_contract.py
mercury/client/model/option_contract_type.py
mercury/client/model/option_leg.py
mercury/client/model/option_single.py
mercury/client/model/pn_l.py
mercury/client/model/pn_l_curve.py
mercury/client/model/position.py
mercury/client/model/spread.py
mercury/client/model/straddle.py
mercury/client/model/strangle.py
mercury/client/model/ticker.py
mercury/client/model/trade.py
mercury/client/model/unbalanced_butterfly.py
mercury/client/model/vertical_spread.py
mercury/envs/__init__.py
mercury/envs/api_client.py
mercury/envs/options_env.py
mercury/envs/utils.py
tests/__init__.py
tests/test_butterfly.py
tests/test_data_point.py
tests/test_date_value_data_point.py
tests/test_date_value_data_point_double.py
tests/test_equity_quote.py
tests/test_fiddle.py
tests/test_fiddle_api.py
tests/test_greeks.py
tests/test_gym_env.py
tests/test_iv_skew.py
tests/test_iv_skew_data_point.py
tests/test_marketdata_api.py
tests/test_option_chain.py
tests/test_option_contract.py
tests/test_option_leg.py
tests/test_option_single.py
tests/test_pn_l.py
tests/test_pn_l_curve.py
tests/test_position.py
tests/test_spread.py
tests/test_straddle.py
tests/test_strangle.py
tests/test_ticker.py
FiddleOptions-1.2.4.dist-info/LICENSE
FiddleOptions-1.2.4.dist-info/METADATA
FiddleOptions-1.2.4.dist-info/WHEEL
FiddleOptions-1.2.4.dist-info/top_level.txt
FiddleOptions-1.2.4.dist-info/RECORD
