Metadata-Version: 2.1
Name: FiddleOptions
Version: 1.2.4
Summary: Fiddle Options Platform
Home-page: https://github.com/vblagoje
Author: Vladimir Blagojevic
Author-email: dovlex@gmail.com
License: UNKNOWN
Keywords: Fiddle Options Platform
Platform: UNKNOWN
Requires-Dist: urllib3 (<1.23,>=1.15)
Requires-Dist: six (>=1.10)
Requires-Dist: pandas
Requires-Dist: certifi
Requires-Dist: python-dateutil
Requires-Dist: gym (>=0.15.3)
Requires-Dist: cachetools (>=3.1.1)
